Metadata-Version: 2.1
Name: example_package_subfolder
Version: 0.0.3
Summary: Another example package
Author-email: Sean Park <saehie.park@gmail.com>
Maintainer-email: Sean Park <saehie.park@gmail.com>
License:                                  Apache License
Project-URL: Homepage, https://github.com/seanshpark/example_package_subfolder/tree/main/compiler/tools/example_package_subfolder/
Project-URL: Bug Reports, https://github.com/seanshpark/example_package_subfolder/issues
Classifier: Programming Language :: Python :: 3
Classifier: License :: OSI Approved :: Apache Software License
Classifier: Operating System :: OS Independent
Requires-Python: >=3.8
License-File: LICENSE
